{
    "snapshot_id":  "screening_rules_v1.2",
    "frozen_at":  "2026-07-16T02:06:34Z",
    "canonical_work_count":  1487,
    "tier_counts":  [
                        {
                            "tier":  "A",
                            "count":  208
                        },
                        {
                            "tier":  "B",
                            "count":  371
                        },
                        {
                            "tier":  "C",
                            "count":  450
                        },
                        {
                            "tier":  "M",
                            "count":  35
                        },
                        {
                            "tier":  "R",
                            "count":  423
                        }
                    ],
    "benchmark_decision":  "pass_freeze_and_start_30_fulltext_pilot",
    "files":  [
                  {
                      "file":  "fulltext_acquisition_queue.csv",
                      "bytes":  245765,
                      "sha256":  "ff419b8d08b8fff7941a03c4762aa06d59261ef3f4311402a2f495a97c8b6e69"
                  },
                  {
                      "file":  "literature.sqlite3",
                      "bytes":  16379904,
                      "sha256":  "c5eecc48b784687093a31e094b9a36239f472fad424b7c6f1ec1810f7d1bbfd9"
                  },
                  {
                      "file":  "literature_master.csv",
                      "bytes":  3160270,
                      "sha256":  "25292a62519ec05c5293d6c71b22ba515fda5d64f166398fe91f41310b30440b"
                  },
                  {
                      "file":  "screening_rules.json",
                      "bytes":  921,
                      "sha256":  "3cf971c1674a47c35fe795c27ac743c9e4f2cd5f2dffb98f603cf81366f48373"
                  }
              ]
}
